README.md
setup.py
youtube_search_scraper/__init__.py
youtube_search_scraper.egg-info/PKG-INFO
youtube_search_scraper.egg-info/SOURCES.txt
youtube_search_scraper.egg-info/dependency_links.txt
youtube_search_scraper.egg-info/requires.txt
youtube_search_scraper.egg-info/top_level.txt