Metadata-Version: 2.1
Name: youtube-search-scraper
Version: 1.0.0
Summary: A python library to search keyword on youtube and get search results automatically.
Home-page: https://youtube-api.datakund.com/en/latest/
Author: DataKund
Author-email: datakund@gmail.com
License: Apache License 2.0
Keywords: youtube python bot_studio automation search search-results web-scraping data
Platform: UNKNOWN
